andriller/__init__.py
andriller/__main__.py
andriller/adb_conn.py
andriller/classes.py
andriller/config.py
andriller/cracking.py
andriller/decoders.py
andriller/decrypts.py
andriller/driller.py
andriller/engines.py
andriller/exceptions.py
andriller/messages.py
andriller/screencap.py
andriller/statics.py
andriller/utils.py
andriller/bin/AdbWinApi.dll
andriller/bin/AdbWinUsbApi.dll
andriller/bin/adb.exe
andriller/bin/lib64/libc++.so
andriller/gui/__init__.py
andriller/gui/core.py
andriller/gui/lockscreens.py
andriller/gui/preferences.py
andriller/gui/screen_cap.py
andriller/gui/tooltips.py
andriller/gui/wa_crypt.py
andriller/gui/windows.py
andriller/res/icon3.gif
andriller/res/icon3.icns
andriller/res/icon3.ico
andriller/res/icon3.png
andriller/res/icon3.xbm
andriller/res/logo.gif
andriller/templates/REPORT.html
andriller/templates/ScreencapReport.html
andriller/templates/_headers.html
andriller/templates/accounts.html
andriller/templates/base.html
andriller/templates/calendar.html
andriller/templates/call_logs.html
andriller/templates/chrome_passwords.html
andriller/templates/downloads.html
andriller/templates/facebook_messages.html
andriller/templates/fb_attach.html
andriller/templates/fb_rcpt.html
andriller/templates/fb_share.html
andriller/templates/fb_sticker.html
andriller/templates/google_photos.html
andriller/templates/kik_messages.html
andriller/templates/samsung_snippets.html
andriller/templates/shared_storage.html
andriller/templates/skype_calls.html
andriller/templates/skype_messages.html
andriller/templates/skype_messages_legacy.html
andriller/templates/sms_messages.html
andriller/templates/style.html
andriller/templates/template.html
andriller/templates/viber_contacts.html
andriller/templates/viber_media.html
andriller/templates/viber_messages.html
andriller/templates/wa_media.html
andriller/templates/web_history.html
andriller/templates/web_passwords.html
andriller/templates/whatsapp_contacts.html
andriller/templates/whatsapp_messages.html
andriller-3.6.3.dist-info/LICENSE
andriller-3.6.3.dist-info/METADATA
andriller-3.6.3.dist-info/WHEEL
andriller-3.6.3.dist-info/top_level.txt
andriller-3.6.3.dist-info/zip-safe
andriller-3.6.3.dist-info/RECORD
