Metadata-Version: 2.1
Name: andriller
Version: 3.6.3
Summary: Andriller CE | Android Forensic Tools
Home-page: https://github.com/den4uk/andriller
Author: Denis Sazonov
Author-email: den@saz.lt
License: MIT License
Keywords: andriller,android,forensic,forensics,adb,dfir
Platform: UNKNOWN
Classifier: Programming Language :: Python :: 3
Classifier: License :: OSI Approved :: MIT License
Classifier: Operating System :: OS Independent
Requires-Python: >=3.6
License-File: LICENSE
Requires-Dist: dateutils
Requires-Dist: javaobj-py3 (>=0.4.3)
Requires-Dist: pycryptodomex
Requires-Dist: python-dateutil
Requires-Dist: XlsxWriter
Requires-Dist: Jinja2 (<3,>=2.11.3)
Requires-Dist: MarkupSafe (==2.0.1)
Requires-Dist: wrapt-timeout-decorator (==1.3.10)
Requires-Dist: appdirs (<2,>=1.4.4)
Requires-Dist: requests
Requires-Dist: dataclasses (>=0.8) ; python_version == "3.6"
